[
  {
    "ticker": "QQQ",
    "country": "United States",
    "tier": "US",
    "fin": 1.19,
    "tech": 66.71,
    "com": 1.62,
    "gdp": 1.99,
    "inflation": 2.24,
    "fx_chg": 0.42,
    "fx_vol": 0.0,
    "roe": 25.93,
    "payout": 20.03,
    "sgr": 20.74,
    "c": 0.949,
    "cad_curr": -3.71,
    "cad_n5y": -3.59,
    "lt_eps": 14.81,
    "beta_gdp": 2.0,
    "pe": 25.57,
    "com_profile": "NEUTRAL"
  },
  {
    "ticker": "SPY",
    "country": "United States",
    "tier": "US",
    "fin": 11.92,
    "tech": 45.1,
    "com": 6.08,
    "gdp": 1.99,
    "inflation": 2.24,
    "fx_chg": 0.42,
    "fx_vol": 0.0,
    "roe": 20.71,
    "payout": 28.78,
    "sgr": 14.75,
    "c": 0.754,
    "cad_curr": -3.71,
    "cad_n5y": -3.59,
    "lt_eps": 12.78,
    "beta_gdp": 1.4,
    "pe": 20.98,
    "com_profile": "NEUTRAL"
  },
  {
    "ticker": "EWC",
    "country": "Canada",
    "tier": "DM",
    "fin": 42.62,
    "tech": 5.22,
    "com": 32.86,
    "gdp": 1.7,
    "inflation": 1.99,
    "fx_chg": -0.57,
    "fx_vol": 5.83,
    "roe": 13.85,
    "payout": 41.72,
    "sgr": 8.07,
    "c": 0.433,
    "cad_curr": -0.22,
    "cad_n5y": -0.25,
    "lt_eps": 10.29,
    "beta_gdp": 1.0,
    "pe": 15.91,
    "com_profile": "MILD_EXP"
  },
  {
    "ticker": "EWA",
    "country": "Australia",
    "tier": "DM",
    "fin": 47.52,
    "tech": 1.67,
    "com": 28.78,
    "gdp": 2.03,
    "inflation": 2.56,
    "fx_chg": -0.15,
    "fx_vol": 8.3,
    "roe": 13.42,
    "payout": 66.65,
    "sgr": 4.48,
    "c": 0.571,
    "cad_curr": -2.31,
    "cad_n5y": -2.33,
    "lt_eps": 4.06,
    "beta_gdp": 1.0,
    "pe": 17.75,
    "com_profile": "BROAD_EXP"
  },
  {
    "ticker": "IEV",
    "country": "Europe",
    "tier": "DM",
    "fin": 25.68,
    "tech": 9.75,
    "com": 12.26,
    "gdp": 1.42,
    "inflation": 2.2,
    "fx_chg": 0.3,
    "fx_vol": 7.17,
    "roe": 13.79,
    "payout": 47.2,
    "sgr": 7.28,
    "c": 0.696,
    "cad_curr": 2.0,
    "cad_n5y": 2.3,
    "lt_eps": 11.46,
    "beta_gdp": 1.0,
    "pe": 14.36,
    "com_profile": "MILD_IMP"
  },
  {
    "ticker": "EWJ",
    "country": "Japan",
    "tier": "DM",
    "fin": 21.19,
    "tech": 22.41,
    "com": 8.11,
    "gdp": 0.63,
    "inflation": 1.98,
    "fx_chg": -3.77,
    "fx_vol": 9.23,
    "roe": 9.46,
    "payout": 34.88,
    "sgr": 6.16,
    "c": 0.465,
    "cad_curr": 3.8,
    "cad_n5y": 3.97,
    "lt_eps": 10.78,
    "beta_gdp": 1.0,
    "pe": 17.09,
    "com_profile": "MILD_IMP"
  },
  {
    "ticker": "EWS",
    "country": "Singapore",
    "tier": "DM",
    "fin": 60.33,
    "tech": 3.33,
    "com": 0.25,
    "gdp": 2.7,
    "inflation": 1.95,
    "fx_chg": 0.71,
    "fx_vol": 3.91,
    "roe": 9.94,
    "payout": 61.58,
    "sgr": 3.82,
    "c": 0.284,
    "cad_curr": 16.57,
    "cad_n5y": 16.41,
    "lt_eps": 4.54,
    "beta_gdp": 1.0,
    "pe": 15.03,
    "com_profile": "MILD_IMP"
  },
  {
    "ticker": "EIS",
    "country": "Israel",
    "tier": "DM",
    "fin": 44.12,
    "tech": 19.26,
    "com": 3.35,
    "gdp": 3.65,
    "inflation": 2.0,
    "fx_chg": 2.72,
    "fx_vol": 6.86,
    "roe": 16.49,
    "payout": 22.02,
    "sgr": 12.86,
    "c": 0.63,
    "cad_curr": 1.94,
    "cad_n5y": 2.56,
    "lt_eps": 14.41,
    "beta_gdp": 1.0,
    "pe": 16.14,
    "com_profile": "MILD_IMP"
  },
  {
    "ticker": "EIDO",
    "country": "Indonesia",
    "tier": "EM",
    "fin": 40.02,
    "tech": 0.22,
    "com": 26.43,
    "gdp": 5.14,
    "inflation": 2.52,
    "fx_chg": -2.67,
    "fx_vol": 3.49,
    "roe": 14.17,
    "payout": 52.42,
    "sgr": 6.74,
    "c": 0.247,
    "cad_curr": -1.06,
    "cad_n5y": -0.81,
    "lt_eps": 10.19,
    "beta_gdp": 1.0,
    "pe": 9.62,
    "com_profile": "BROAD_EXP"
  },
  {
    "ticker": "EPOL",
    "country": "Poland",
    "tier": "EM HR",
    "fin": 46.24,
    "tech": 4.66,
    "com": 13.17,
    "gdp": 2.64,
    "inflation": 2.7,
    "fx_chg": 0.75,
    "fx_vol": 8.84,
    "roe": 12.42,
    "payout": 39.41,
    "sgr": 7.52,
    "c": 0.174,
    "cad_curr": -1.11,
    "cad_n5y": -0.81,
    "lt_eps": 15.14,
    "beta_gdp": 1.0,
    "pe": 10.67,
    "com_profile": "MILD_IMP"
  },
  {
    "ticker": "EWT",
    "country": "Taiwan",
    "tier": "EM",
    "fin": 13.13,
    "tech": 69.34,
    "com": 6.8,
    "gdp": 2.92,
    "inflation": 1.56,
    "fx_chg": 0.32,
    "fx_vol": 5.4,
    "roe": 13.77,
    "payout": 54.53,
    "sgr": 6.26,
    "c": 0.632,
    "cad_curr": 18.12,
    "cad_n5y": 16.65,
    "lt_eps": 17.02,
    "beta_gdp": 1.0,
    "pe": 21.67,
    "com_profile": "MILD_IMP"
  },
  {
    "ticker": "EWW",
    "country": "Mexico",
    "tier": "EM",
    "fin": 25.81,
    "tech": 0.07,
    "com": 21.71,
    "gdp": 2.0,
    "inflation": 3.0,
    "fx_chg": 0.45,
    "fx_vol": 13.19,
    "roe": 13.81,
    "payout": 49.91,
    "sgr": 6.92,
    "c": 0.769,
    "cad_curr": -0.36,
    "cad_n5y": -0.63,
    "lt_eps": 14.56,
    "beta_gdp": 1.4,
    "pe": 13.53,
    "com_profile": "MILD_EXP"
  },
  {
    "ticker": "EWY",
    "country": "South Korea",
    "tier": "EM",
    "fin": 11.29,
    "tech": 52.05,
    "com": 4.06,
    "gdp": 1.98,
    "inflation": 1.96,
    "fx_chg": -2.39,
    "fx_vol": 6.07,
    "roe": 11.91,
    "payout": 20.22,
    "sgr": 9.51,
    "c": 0.433,
    "cad_curr": 5.58,
    "cad_n5y": 5.43,
    "lt_eps": 18.09,
    "beta_gdp": 1.0,
    "pe": 8.13,
    "com_profile": "HEAVY_IMP"
  },
  {
    "ticker": "EWZ",
    "country": "Brazil",
    "tier": "EM HR",
    "fin": 35.6,
    "tech": 0.74,
    "com": 31.2,
    "gdp": 2.29,
    "inflation": 3.0,
    "fx_chg": -3.2,
    "fx_vol": 16.92,
    "roe": 19.72,
    "payout": 50.54,
    "sgr": 9.75,
    "c": 0.634,
    "cad_curr": -2.71,
    "cad_n5y": -2.02,
    "lt_eps": 8.26,
    "beta_gdp": 1.0,
    "pe": 8.89,
    "com_profile": "BROAD_EXP"
  },
  {
    "ticker": "EZA",
    "country": "South Africa",
    "tier": "EM HR",
    "fin": 36.72,
    "tech": 1.38,
    "com": 39.67,
    "gdp": 1.53,
    "inflation": 2.99,
    "fx_chg": -0.94,
    "fx_vol": 16.03,
    "roe": 17.75,
    "payout": 41.19,
    "sgr": 10.44,
    "c": 0.369,
    "cad_curr": -0.89,
    "cad_n5y": -1.67,
    "lt_eps": 11.23,
    "beta_gdp": 1.0,
    "pe": 8.99,
    "com_profile": "MILD_EXP"
  },
  {
    "ticker": "GREK",
    "country": "Greece",
    "tier": "EM HR",
    "fin": 48.08,
    "tech": 0.02,
    "com": 12.98,
    "gdp": 1.64,
    "inflation": 2.19,
    "fx_chg": 0.3,
    "fx_vol": 7.17,
    "roe": 11.3,
    "payout": 39.17,
    "sgr": 6.87,
    "c": 1.0,
    "cad_curr": -6.39,
    "cad_n5y": -4.69,
    "lt_eps": 10.42,
    "beta_gdp": 1.0,
    "pe": 10.05,
    "com_profile": "MILD_IMP"
  },
  {
    "ticker": "TUR",
    "country": "Turkey",
    "tier": "EM HR",
    "fin": 29.07,
    "tech": 0.21,
    "com": 20.41,
    "gdp": 3.79,
    "inflation": 15.84,
    "fx_chg": -23.97,
    "fx_vol": 23.18,
    "roe": 18.16,
    "payout": 25.62,
    "sgr": 13.5,
    "c": 0.391,
    "cad_curr": -2.85,
    "cad_n5y": -1.82,
    "lt_eps": 10.0,
    "beta_gdp": 1.0,
    "pe": 8.57,
    "com_profile": "HEAVY_IMP"
  },
  {
    "ticker": "THD",
    "country": "Thailand",
    "tier": "EM",
    "fin": 16.59,
    "tech": 11.46,
    "com": 20.47,
    "gdp": 2.22,
    "inflation": 1.6,
    "fx_chg": 0.89,
    "fx_vol": 6.51,
    "roe": 9.5,
    "payout": 52.55,
    "sgr": 4.51,
    "c": 0.452,
    "cad_curr": 0.71,
    "cad_n5y": 2.16,
    "lt_eps": 5.54,
    "beta_gdp": 1.0,
    "pe": 16.6,
    "com_profile": "HEAVY_IMP"
  },
  {
    "ticker": "ECH",
    "country": "Chile",
    "tier": "EM HR",
    "fin": 34.01,
    "tech": 0.0,
    "com": 23.93,
    "gdp": 2.36,
    "inflation": 3.0,
    "fx_chg": -2.86,
    "fx_vol": 12.88,
    "roe": 11.41,
    "payout": 49.34,
    "sgr": 5.78,
    "c": 0.375,
    "cad_curr": -0.77,
    "cad_n5y": -2.06,
    "lt_eps": 18.82,
    "beta_gdp": 1.0,
    "pe": 12.18,
    "com_profile": "BROAD_EXP"
  },
  {
    "ticker": "EMXC",
    "country": "Emerging x China",
    "tier": "EM",
    "fin": 21.25,
    "tech": 44.65,
    "com": 11.08,
    "gdp": 4.03,
    "inflation": 3.0,
    "fx_chg": -0.73,
    "fx_vol": 7.72,
    "roe": 14.78,
    "payout": 38.64,
    "sgr": 9.07,
    "c": 0.485,
    "cad_curr": 1.01,
    "cad_n5y": 0.67,
    "lt_eps": 16.13,
    "beta_gdp": 1.0,
    "pe": 12.07,
    "com_profile": "NEUTRAL"
  },
  {
    "ticker": "MCHI",
    "country": "China",
    "tier": "EM",
    "fin": 24.82,
    "tech": 23.47,
    "com": 8.92,
    "gdp": 3.79,
    "inflation": 1.89,
    "fx_chg": -0.45,
    "fx_vol": 5.73,
    "roe": 11.75,
    "payout": 27.21,
    "sgr": 8.55,
    "c": 0.43,
    "cad_curr": 3.48,
    "cad_n5y": 2.98,
    "lt_eps": 13.54,
    "beta_gdp": 1.0,
    "pe": 11.92,
    "com_profile": "NEUTRAL"
  },
  {
    "ticker": "INDA",
    "country": "India",
    "tier": "EM",
    "fin": 30.58,
    "tech": 8.54,
    "com": 15.95,
    "gdp": 6.51,
    "inflation": 4.0,
    "fx_chg": -3.44,
    "fx_vol": 4.11,
    "roe": 14.94,
    "payout": 31.32,
    "sgr": 10.26,
    "c": 0.45,
    "cad_curr": -2.03,
    "cad_n5y": -1.64,
    "lt_eps": 17.86,
    "beta_gdp": 1.0,
    "pe": 21.25,
    "com_profile": "HEAVY_IMP"
  }
]